Workbook

Sheet Sheet
A1: Planilhas do Salão
A2: Preencha só as células AMARELAS. As células coloridas são calculadas sozinhas.
A4: COMO USAR
A5: 1. Aba 'Metas': preencha a estrutura do salão e descubra sua ocupação e quantos atendimentos por dia você precisa.
A6: 2. Aba 'Precificação': coloque seus custos fixos e seus serviços. Os serviços em VERMELHO estão abaixo do preço mínimo.
A7: 3. Aba 'Ciclos': confira de quantos em quantos dias cada serviço deve voltar (já vem preenchida, ajuste se quiser).
A8: 4. Aba 'Clientes': cadastre suas clientes com a data da última visita. A coluna Status diz quem chamar hoje.
A9: • Em dia: ainda não é hora. • Chamar agora: passou do prazo (use o Prompt 28). • Sumida: 15 a 60 dias de atraso (Prompts 29 e 30). • Reativar: mais de 60 dias (Prompt 31).
A10: 5. Aba 'Calendário 30 dias': o que postar em cada dia, com o prompt certo. Marque 'Feito'.
A11: 6. Aba 'Campanhas do ano': datas para planejar com 3 a 4 semanas de antecedência (Prompt 41).
A12: 7. Aba 'Vales e Pacotes': controle os vale-presentes e pacotes vendidos, com validade automática.
A14: DICAS
... A17: • As datas devem ser digitadas no formato dia/mês/ano, ex.: 15/09/2026.

Sheet Ciclos
A1: Ciclo de retorno por serviço
A2: Em quantos dias a cliente normalmente deve voltar. Ajuste à sua realidade.
A4: Serviço | B4: Ciclo (dias)
A5: Manicure | B5: 10
A6: Pedicure | B6: 15
A7: Manicure e pedicure | B7: 12
A8: Escova | B8: 7
A9: Unhas em gel (manutenção) | B9: 25
A10: Design de sobrancelha | B10: 20
A11: Retoque de raiz | B11: 35
A12: Coloração | B12: 45
A13: Corte feminino | B13: 60
A14: Corte masculino | B14: 30
A15: Barba | B15: 15
A16: Mechas / luzes | B16: 90
... A20: Depilação | B20: 30

Sheet Clientes
A1: Clientes: quem chamar hoje
A2: Preencha nome, serviço e última visita. O status é calculado sozinho.
A4: Nome | B4: WhatsApp | C4: Serviço principal | D4: Última visita | E4: Ciclo (dias) | F4: Próximo retorno | G4: Dias de atraso | H4: Status | I4: Aniversário | J4: Mês aniv. | K4: Observações | M4: RESUMO
A5: Ana (exemplo) | B5: 11 99999-0001 | C5: Manicure | D5: =TODAY()-20 | E5: =IF(C5="","",IFERROR(VLOOKUP(C5,Ciclos!$A$5:$B$29,2,FALSE),"")) | F5: =IF(OR(D5="",E5=""),"",D5+E5) | G5: =IF(F5="","",TODAY()-F5) | H5: =IF(F5="","",IF(G5<0,"Em dia",IF(G5<=15,"Chamar agora",IF(G5<=60,"Sumida","Reativar")))) | J5: =IF(I5="","",MONTH(I5)) | M5: Clientes cadastradas | N5: =COUNTA(A5:A404)
A6: Carla (exemplo) | B6: 11 99999-0002 | C6: Retoque de raiz | D6: =TODAY()-40 | E6: =IF(C6="","",IFERROR(VLOOKUP(C6,Ciclos!$A$5:$B$29,2,FALSE),"")) | F6: =IF(OR(D6="",E6=""),"",D6+E6) | G6: =IF(F6="","",TODAY()-F6) | H6: =IF(F6="","",IF(G6<0,"Em dia",IF(G6<=15,"Chamar agora",IF(G6<=60,"Sumida","Reativar")))) | J6: =IF(I6="","",MONTH(I6)) | M6: Em dia | N6: =COUNTIF(H5:H404,"Em dia")
A7: Bia (exemplo) | B7: 11 99999-0003 | C7: Progressiva / alisamento | D7: =TODAY()-30 | E7: =IF(C7="","",IFERROR(VLOOKUP(C7,Ciclos!$A$5:$B$29,2,FALSE),"")) | F7: =IF(OR(D7="",E7=""),"",D7+E7) | G7: =IF(F7="","",TODAY()-F7) | H7: =IF(F7="","",IF(G7<0,"Em dia",IF(G7<=15,"Chamar agora",IF(G7<=60,"Sumida","Reativar")))) | J7: =IF(I7="","",MONTH(I7)) | M7: Chamar agora | N7: =COUNTIF(H5:H404,"Chamar agora")
E8: =IF(C8="","",IFERROR(VLOOKUP(C8,Ciclos!$A$5:$B$29,2,FALSE),"")) | F8: =IF(OR(D8="",E8=""),"",D8+E8) | G8: =IF(F8="","",TODAY()-F8) | H8: =IF(F8="","",IF(G8<0,"Em dia",IF(G8<=15,"Chamar agora",IF(G8<=60,"Sumida","Reativar")))) | J8: =IF(I8="","",MONTH(I8)) | M8: Sumidas | N8: =COUNTIF(H5:H404,"Sumida")
E9: =IF(C9="","",IFERROR(VLOOKUP(C9,Ciclos!$A$5:$B$29,2,FALSE),"")) | F9: =IF(OR(D9="",E9=""),"",D9+E9) | G9: =IF(F9="","",TODAY()-F9) | H9: =IF(F9="","",IF(G9<0,"Em dia",IF(G9<=15,"Chamar agora",IF(G9<=60,"Sumida","Reativar")))) | J9: =IF(I9="","",MONTH(I9)) | M9: Reativar (60+ dias) | N9: =COUNTIF(H5:H404,"Reativar")
E10: =IF(C10="","",IFERROR(VLOOKUP(C10,Ciclos!$A$5:$B$29,2,FALSE),"")) | F10: =IF(OR(D10="",E10=""),"",D10+E10) | G10: =IF(F10="","",TODAY()-F10) | H10: =IF(F10="","",IF(G10<0,"Em dia",IF(G10<=15,"Chamar agora",IF(G10<=60,"Sumida","Reativar")))) | J10: =IF(I10="","",MONTH(I10)) | M10: Aniversariantes do mês | N10: =COUNTIF(J5:J404,MONTH(TODAY()))
E11: =IF(C11="","",IFERROR(VLOOKUP(C11,Ciclos!$A$5:$B$29,2,FALSE),"")) | F11: =IF(OR(D11="",E11=""),"",D11+E11) | G11: =IF(F11="","",TODAY()-F11) | H11: =IF(F11="","",IF(G11<0,"Em dia",IF(G11<=15,"Chamar agora",IF(G11<=60,"Sumida","Reativar")))) | J11: =IF(I11="","",MONTH(I11))
E12: =IF(C12="","",IFERROR(VLOOKUP(C12,Ciclos!$A$5:$B$29,2,FALSE),"")) | F12: =IF(OR(D12="",E12=""),"",D12+E12) | G12: =IF(F12="","",TODAY()-F12) | H12: =IF(F12="","",IF(G12<0,"Em dia",IF(G12<=15,"Chamar agora",IF(G12<=60,"Sumida","Reativar")))) | J12: =IF(I12="","",MONTH(I12)) | M12: Apague as 3 linhas de exemplo quando começar.
E13: =IF(C13="","",IFERROR(VLOOKUP(C13,Ciclos!$A$5:$B$29,2,FALSE),"")) | F13: =IF(OR(D13="",E13=""),"",D13+E13) | G13: =IF(F13="","",TODAY()-F13) | H13: =IF(F13="","",IF(G13<0,"Em dia",IF(G13<=15,"Chamar agora",IF(G13<=60,"Sumida","Reativar")))) | J13: =IF(I13="","",MONTH(I13)) | M13: Dica: use Dados > Filtro na linha 4 para ver só 'Chamar agora'.
E14: =IF(C14="","",IFERROR(VLOOKUP(C14,Ciclos!$A$5:$B$29,2,FALSE),"")) | F14: =IF(OR(D14="",E14=""),"",D14+E14) | G14: =IF(F14="","",TODAY()-F14) | H14: =IF(F14="","",IF(G14<0,"Em dia",IF(G14<=15,"Chamar agora",IF(G14<=60,"Sumida","Reativar")))) | J14: =IF(I14="","",MONTH(I14))
E15: =IF(C15="","",IFERROR(VLOOKUP(C15,Ciclos!$A$5:$B$29,2,FALSE),"")) | F15: =IF(OR(D15="",E15=""),"",D15+E15) | G15: =IF(F15="","",TODAY()-F15) | H15: =IF(F15="","",IF(G15<0,"Em dia",IF(G15<=15,"Chamar agora",IF(G15<=60,"Sumida","Reativar")))) | J15: =IF(I15="","",MONTH(I15))
E16: =IF(C16="","",IFERROR(VLOOKUP(C16,Ciclos!$A$5:$B$29,2,FALSE),"")) | F16: =IF(OR(D16="",E16=""),"",D16+E16) | G16: =IF(F16="","",TODAY()-F16) | H16: =IF(F16="","",IF(G16<0,"Em dia",IF(G16<=15,"Chamar agora",IF(G16<=60,"Sumida","Reativar")))) | J16: =IF(I16="","",MONTH(I16))
E17: =IF(C17="","",IFERROR(VLOOKUP(C17,Ciclos!$A$5:$B$29,2,FALSE),"")) | F17: =IF(OR(D17="",E17=""),"",D17+E17) | G17: =IF(F17="","",TODAY()-F17) | H17: =IF(F17="","",IF(G17<0,"Em dia",IF(G17<=15,"Chamar agora",IF(G17<=60,"Sumida","Reativar")))) | J17: =IF(I17="","",MONTH(I17))
E18: =IF(C18="","",IFERROR(VLOOKUP(C18,Ciclos!$A$5:$B$29,2,FALSE),"")) | F18: =IF(OR(D18="",E18=""),"",D18+E18) | G18: =IF(F18="","",TODAY()-F18) | H18: =IF(F18="","",IF(G18<0,"Em dia",IF(G18<=15,"Chamar agora",IF(G18<=60,"Sumida","Reativar")))) | J18: =IF(I18="","",MONTH(I18))
E19: =IF(C19="","",IFERROR(VLOOKUP(C19,Ciclos!$A$5:$B$29,2,FALSE),"")) | F19: =IF(OR(D19="",E19=""),"",D19+E19) | G19: =IF(F19="","",TODAY()-F19) | H19: =IF(F19="","",IF(G19<0,"Em dia",IF(G19<=15,"Chamar agora",IF(G19<=60,"Sumida","Reativar")))) | J19: =IF(I19="","",MONTH(I19))
E20: =IF(C20="","",IFERROR(VLOOKUP(C20,Ciclos!$A$5:$B$29,2,FALSE),"")) | F20: =IF(OR(D20="",E20=""),"",D20+E20) | G20: =IF(F20="","",TODAY()-F20) | H20: =IF(F20="","",IF(G20<0,"Em dia",IF(G20<=15,"Chamar agora",IF(G20<=60,"Sumida","Reativar")))) | J20: =IF(I20="","",MONTH(I20))
E21: =IF(C21="","",IFERROR(VLOOKUP(C21,Ciclos!$A$5:$B$29,2,FALSE),"")) | F21: =IF(OR(D21="",E21=""),"",D21+E21) | G21: =IF(F21="","",TODAY()-F21) | H21: =IF(F21="","",IF(G21<0,"Em dia",IF(G21<=15,"Chamar agora",IF(G21<=60,"Sumida","Reativar")))) | J21: =IF(I21="","",MONTH(I21))
E22: =IF(C22="","",IFERROR(VLOOKUP(C22,Ciclos!$A$5:$B$29,2,FALSE),"")) | F22: =IF(OR(D22="",E22=""),"",D22+E22) | G22: =IF(F22="","",TODAY()-F22) | H22: =IF(F22="","",IF(G22<0,"Em dia",IF(G22<=15,"Chamar agora",IF(G22<=60,"Sumida","Reativar")))) | J22: =IF(I22="","",MONTH(I22))
E23: =IF(C23="","",IFERROR(VLOOKUP(C23,Ciclos!$A$5:$B$29,2,FALSE),"")) | F23: =IF(OR(D23="",E23=""),"",D23+E23) | G23: =IF(F23="","",TODAY()-F23) | H23: =IF(F23="","",IF(G23<0,"Em dia",IF(G23<=15,"Chamar agora",IF(G23<=60,"Sumida","Reativar")))) | J23: =IF(I23="","",MONTH(I23))
E24: =IF(C24="","",IFERROR(VLOOKUP(C24,Ciclos!$A$5:$B$29,2,FALSE),"")) | F24: =IF(OR(D24="",E24=""),"",D24+E24) | G24: =IF(F24="","",TODAY()-F24) | H24: =IF(F24="","",IF(G24<0,"Em dia",IF(G24<=15,"Chamar agora",IF(G24<=60,"Sumida","Reativar")))) | J24: =IF(I24="","",MONTH(I24))
E25: =IF(C25="","",IFERROR(VLOOKUP(C25,Ciclos!$A$5:$B$29,2,FALSE),"")) | F25: =IF(OR(D25="",E25=""),"",D25+E25) | G25: =IF(F25="","",TODAY()-F25) | H25: =IF(F25="","",IF(G25<0,"Em dia",IF(G25<=15,"Chamar agora",IF(G25<=60,"Sumida","Reativar")))) | J25: =IF(I25="","",MONTH(I25))
... E404: =IF(C404="","",IFERROR(VLOOKUP(C404,Ciclos!$A$5:$B$29,2,FALSE),"")) | F404: =IF(OR(D404="",E404=""),"",D404+E404) | G404: =IF(F404="","",TODAY()-F404) | H404: =IF(F404="","",IF(G404<0,"Em dia",IF(G404<=15,"Chamar agora",IF(G404<=60,"Sumida","Reativar")))) | J404: =IF(I404="","",MONTH(I404))

Sheet Precificação
A1: Precificação: o preço mínimo de cada serviço
A2: Preço mínimo = (custo do tempo + produto) ÷ (1 − comissão − taxa − margem)
A4: CUSTOS FIXOS DO MÊS | D4: PARÂMETROS
A5: Aluguel | B5: 2500 | D5: Horas produtivas no mês (atendendo de fato) | E5: 250
A6: Condomínio / IPTU | B6: 300 | D6: Comissão padrão da profissional | E6: 0.4
A7: Luz | B7: 450 | D7: Taxa média do cartão / maquininha | E7: 0.03
A8: Água | B8: 150 | D8: Margem de lucro desejada | E8: 0.2
A9: Internet e telefone | B9: 150
A10: Contador e sistema | B10: 350 | D10: Custo por hora | E10: =IF(E5=0,0,B16/E5)
A11: Pró-labore (seu salário) | B11: 3000 | D11: Custo por minuto | E11: =E10/60
A12: Salários fixos + encargos | B12: 0
A13: Limpeza e manutenção | B13: 300 | D13: Horas produtivas: some as horas em que cada profissional está atendendo no mês.
A14: Marketing | B14: 300 | D14: Os valores já preenchidos são EXEMPLOS. Troque pelos seus.
A15: Outros | B15: 500
A16: Total de custos fixos | B16: =SUM(B5:B15)
A19: Serviço | B19: Duração (min) | C19: Custo do produto | D19: Comissão % | E19: Preço atual | F19: Custo do tempo | G19: PREÇO MÍNIMO | H19: Diferença | I19: Lucro por atendimento | J19: Margem real | K19: Situação
A20: Escova | B20: 45 | C20: 6 | E20: 60 | F20: =IF(B20="","",B20*$E$11) | G20: =IF(B20="","",IFERROR((F20+C20)/(1-IF(D20="",$E$6,D20)-$E$7-$E$8),"verifique %")) | H20: =IF(OR(E20="",B20=""),"",E20-G20) | I20: =IF(OR(E20="",B20=""),"",E20*(1-IF(D20="",$E$6,D20)-$E$7)-F20-C20) | J20: =IF(OR(E20="",E20=0,B20=""),"",I20/E20) | K20: =IF(OR(E20="",B20=""),"",IF(E20<G20,"ABAIXO DO MÍNIMO",IF(E20<G20*1.15,"No limite","Saudável")))
A21: Corte feminino | B21: 50 | C21: 3 | E21: 90 | F21: =IF(B21="","",B21*$E$11) | G21: =IF(B21="","",IFERROR((F21+C21)/(1-IF(D21="",$E$6,D21)-$E$7-$E$8),"verifique %")) | H21: =IF(OR(E21="",B21=""),"",E21-G21) | I21: =IF(OR(E21="",B21=""),"",E21*(1-IF(D21="",$E$6,D21)-$E$7)-F21-C21) | J21: =IF(OR(E21="",E21=0,B21=""),"",I21/E21) | K21: =IF(OR(E21="",B21=""),"",IF(E21<G21,"ABAIXO DO MÍNIMO",IF(E21<G21*1.15,"No limite","Saudável")))
A22: Coloração | B22: 120 | C22: 45 | E22: 180 | F22: =IF(B22="","",B22*$E$11) | G22: =IF(B22="","",IFERROR((F22+C22)/(1-IF(D22="",$E$6,D22)-$E$7-$E$8),"verifique %")) | H22: =IF(OR(E22="",B22=""),"",E22-G22) | I22: =IF(OR(E22="",B22=""),"",E22*(1-IF(D22="",$E$6,D22)-$E$7)-F22-C22) | J22: =IF(OR(E22="",E22=0,B22=""),"",I22/E22) | K22: =IF(OR(E22="",B22=""),"",IF(E22<G22,"ABAIXO DO MÍNIMO",IF(E22<G22*1.15,"No limite","Saudável")))
A23: Manicure | B23: 40 | C23: 4 | E23: 35 | F23: =IF(B23="","",B23*$E$11) | G23: =IF(B23="","",IFERROR((F23+C23)/(1-IF(D23="",$E$6,D23)-$E$7-$E$8),"verifique %")) | H23: =IF(OR(E23="",B23=""),"",E23-G23) | I23: =IF(OR(E23="",B23=""),"",E23*(1-IF(D23="",$E$6,D23)-$E$7)-F23-C23) | J23: =IF(OR(E23="",E23=0,B23=""),"",I23/E23) | K23: =IF(OR(E23="",B23=""),"",IF(E23<G23,"ABAIXO DO MÍNIMO",IF(E23<G23*1.15,"No limite","Saudável")))
A24: Progressiva | B24: 180 | C24: 70 | E24: 250 | F24: =IF(B24="","",B24*$E$11) | G24: =IF(B24="","",IFERROR((F24+C24)/(1-IF(D24="",$E$6,D24)-$E$7-$E$8),"verifique %")) | H24: =IF(OR(E24="",B24=""),"",E24-G24) | I24: =IF(OR(E24="",B24=""),"",E24*(1-IF(D24="",$E$6,D24)-$E$7)-F24-C24) | J24: =IF(OR(E24="",E24=0,B24=""),"",I24/E24) | K24: =IF(OR(E24="",B24=""),"",IF(E24<G24,"ABAIXO DO MÍNIMO",IF(E24<G24*1.15,"No limite","Saudável")))
F25: =IF(B25="","",B25*$E$11) | G25: =IF(B25="","",IFERROR((F25+C25)/(1-IF(D25="",$E$6,D25)-$E$7-$E$8),"verifique %")) | H25: =IF(OR(E25="",B25=""),"",E25-G25) | I25: =IF(OR(E25="",B25=""),"",E25*(1-IF(D25="",$E$6,D25)-$E$7)-F25-C25) | J25: =IF(OR(E25="",E25=0,B25=""),"",I25/E25) | K25: =IF(OR(E25="",B25=""),"",IF(E25<G25,"ABAIXO DO MÍNIMO",IF(E25<G25*1.15,"No limite","Saudável")))
F26: =IF(B26="","",B26*$E$11) | G26: =IF(B26="","",IFERROR((F26+C26)/(1-IF(D26="",$E$6,D26)-$E$7-$E$8),"verifique %")) | H26: =IF(OR(E26="",B26=""),"",E26-G26) | I26: =IF(OR(E26="",B26=""),"",E26*(1-IF(D26="",$E$6,D26)-$E$7)-F26-C26) | J26: =IF(OR(E26="",E26=0,B26=""),"",I26/E26) | K26: =IF(OR(E26="",B26=""),"",IF(E26<G26,"ABAIXO DO MÍNIMO",IF(E26<G26*1.15,"No limite","Saudável")))
F27: =IF(B27="","",B27*$E$11) | G27: =IF(B27="","",IFERROR((F27+C27)/(1-IF(D27="",$E$6,D27)-$E$7-$E$8),"verifique %")) | H27: =IF(OR(E27="",B27=""),"",E27-G27) | I27: =IF(OR(E27="",B27=""),"",E27*(1-IF(D27="",$E$6,D27)-$E$7)-F27-C27) | J27: =IF(OR(E27="",E27=0,B27=""),"",I27/E27) | K27: =IF(OR(E27="",B27=""),"",IF(E27<G27,"ABAIXO DO MÍNIMO",IF(E27<G27*1.15,"No limite","Saudável")))
F28: =IF(B28="","",B28*$E$11) | G28: =IF(B28="","",IFERROR((F28+C28)/(1-IF(D28="",$E$6,D28)-$E$7-$E$8),"verifique %")) | H28: =IF(OR(E28="",B28=""),"",E28-G28) | I28: =IF(OR(E28="",B28=""),"",E28*(1-IF(D28="",$E$6,D28)-$E$7)-F28-C28) | J28: =IF(OR(E28="",E28=0,B28=""),"",I28/E28) | K28: =IF(OR(E28="",B28=""),"",IF(E28<G28,"ABAIXO DO MÍNIMO",IF(E28<G28*1.15,"No limite","Saudável")))
F29: =IF(B29="","",B29*$E$11) | G29: =IF(B29="","",IFERROR((F29+C29)/(1-IF(D29="",$E$6,D29)-$E$7-$E$8),"verifique %")) | H29: =IF(OR(E29="",B29=""),"",E29-G29) | I29: =IF(OR(E29="",B29=""),"",E29*(1-IF(D29="",$E$6,D29)-$E$7)-F29-C29) | J29: =IF(OR(E29="",E29=0,B29=""),"",I29/E29) | K29: =IF(OR(E29="",B29=""),"",IF(E29<G29,"ABAIXO DO MÍNIMO",IF(E29<G29*1.15,"No limite","Saudável")))
F30: =IF(B30="","",B30*$E$11) | G30: =IF(B30="","",IFERROR((F30+C30)/(1-IF(D30="",$E$6,D30)-$E$7-$E$8),"verifique %")) | H30: =IF(OR(E30="",B30=""),"",E30-G30) | I30: =IF(OR(E30="",B30=""),"",E30*(1-IF(D30="",$E$6,D30)-$E$7)-F30-C30) | J30: =IF(OR(E30="",E30=0,B30=""),"",I30/E30) | K30: =IF(OR(E30="",B30=""),"",IF(E30<G30,"ABAIXO DO MÍNIMO",IF(E30<G30*1.15,"No limite","Saudável")))
F31: =IF(B31="","",B31*$E$11) | G31: =IF(B31="","",IFERROR((F31+C31)/(1-IF(D31="",$E$6,D31)-$E$7-$E$8),"verifique %")) | H31: =IF(OR(E31="",B31=""),"",E31-G31) | I31: =IF(OR(E31="",B31=""),"",E31*(1-IF(D31="",$E$6,D31)-$E$7)-F31-C31) | J31: =IF(OR(E31="",E31=0,B31=""),"",I31/E31) | K31: =IF(OR(E31="",B31=""),"",IF(E31<G31,"ABAIXO DO MÍNIMO",IF(E31<G31*1.15,"No limite","Saudável")))
F32: =IF(B32="","",B32*$E$11) | G32: =IF(B32="","",IFERROR((F32+C32)/(1-IF(D32="",$E$6,D32)-$E$7-$E$8),"verifique %")) | H32: =IF(OR(E32="",B32=""),"",E32-G32) | I32: =IF(OR(E32="",B32=""),"",E32*(1-IF(D32="",$E$6,D32)-$E$7)-F32-C32) | J32: =IF(OR(E32="",E32=0,B32=""),"",I32/E32) | K32: =IF(OR(E32="",B32=""),"",IF(E32<G32,"ABAIXO DO MÍNIMO",IF(E32<G32*1.15,"No limite","Saudável")))
F33: =IF(B33="","",B33*$E$11) | G33: =IF(B33="","",IFERROR((F33+C33)/(1-IF(D33="",$E$6,D33)-$E$7-$E$8),"verifique %")) | H33: =IF(OR(E33="",B33=""),"",E33-G33) | I33: =IF(OR(E33="",B33=""),"",E33*(1-IF(D33="",$E$6,D33)-$E$7)-F33-C33) | J33: =IF(OR(E33="",E33=0,B33=""),"",I33/E33) | K33: =IF(OR(E33="",B33=""),"",IF(E33<G33,"ABAIXO DO MÍNIMO",IF(E33<G33*1.15,"No limite","Saudável")))
F34: =IF(B34="","",B34*$E$11) | G34: =IF(B34="","",IFERROR((F34+C34)/(1-IF(D34="",$E$6,D34)-$E$7-$E$8),"verifique %")) | H34: =IF(OR(E34="",B34=""),"",E34-G34) | I34: =IF(OR(E34="",B34=""),"",E34*(1-IF(D34="",$E$6,D34)-$E$7)-F34-C34) | J34: =IF(OR(E34="",E34=0,B34=""),"",I34/E34) | K34: =IF(OR(E34="",B34=""),"",IF(E34<G34,"ABAIXO DO MÍNIMO",IF(E34<G34*1.15,"No limite","Saudável")))
F35: =IF(B35="","",B35*$E$11) | G35: =IF(B35="","",IFERROR((F35+C35)/(1-IF(D35="",$E$6,D35)-$E$7-$E$8),"verifique %")) | H35: =IF(OR(E35="",B35=""),"",E35-G35) | I35: =IF(OR(E35="",B35=""),"",E35*(1-IF(D35="",$E$6,D35)-$E$7)-F35-C35) | J35: =IF(OR(E35="",E35=0,B35=""),"",I35/E35) | K35: =IF(OR(E35="",B35=""),"",IF(E35<G35,"ABAIXO DO MÍNIMO",IF(E35<G35*1.15,"No limite","Saudável")))
F36: =IF(B36="","",B36*$E$11) | G36: =IF(B36="","",IFERROR((F36+C36)/(1-IF(D36="",$E$6,D36)-$E$7-$E$8),"verifique %")) | H36: =IF(OR(E36="",B36=""),"",E36-G36) | I36: =IF(OR(E36="",B36=""),"",E36*(1-IF(D36="",$E$6,D36)-$E$7)-F36-C36) | J36: =IF(OR(E36="",E36=0,B36=""),"",I36/E36) | K36: =IF(OR(E36="",B36=""),"",IF(E36<G36,"ABAIXO DO MÍNIMO",IF(E36<G36*1.15,"No limite","Saudável")))
... F39: =IF(B39="","",B39*$E$11) | G39: =IF(B39="","",IFERROR((F39+C39)/(1-IF(D39="",$E$6,D39)-$E$7-$E$8),"verifique %")) | H39: =IF(OR(E39="",B39=""),"",E39-G39) | I39: =IF(OR(E39="",B39=""),"",E39*(1-IF(D39="",$E$6,D39)-$E$7)-F39-C39) | J39: =IF(OR(E39="",E39=0,B39=""),"",I39/E39) | K39: =IF(OR(E39="",B39=""),"",IF(E39<G39,"ABAIXO DO MÍNIMO",IF(E39<G39*1.15,"No limite","Saudável")))
A41: Comissão % em branco = usa a comissão padrão. Lucro por atendimento já desconta comissão, taxa, tempo e produto.

Sheet Metas
A1: Metas e ocupação
A2: Descubra quanto da sua agenda está sendo usada e quanto falta para a meta.
A4: Número de profissionais atendendo | B4: 2
A5: Horas de trabalho por dia (cada) | B5: 8
A6: Dias trabalhados no mês | B6: 22
A7: Atendimentos realizados no mês | B7: 180
A8: Duração média de um atendimento (min) | B8: 60
A9: Faturamento do mês (R$) | B9: 16200
A10: Meta de faturamento do mês (R$) | B10: 22000
A12: Horas disponíveis no mês | B12: =B4*B5*B6
A13: Horas atendidas no mês | B13: =B7*B8/60
A14: TAXA DE OCUPAÇÃO | B14: =IF(B12=0,0,B13/B12)
A15: Ticket médio (R$) | B15: =IF(B7=0,0,B9/B7)
A16: Atendimentos necessários para a meta | B16: =IF(B15=0,0,ROUNDUP(B10/B15,0))
A17: Atendimentos a mais por mês | B17: =MAX(0,B16-B7)
A18: Atendimentos a mais por dia | B18: =IF(B6=0,0,ROUNDUP(B17/B6,1))
A19: Ocupação necessária para a meta | B19: =IF(B12=0,0,B16*B8/60/B12)
A20: Diagnóstico | B20: =IF(B19>1,"Meta exige mais que 100% da agenda: suba o ticket (combos, preço) ou a equipe",IF(B14<0.6,"Ocupação baixa: foque em retenção e divulgação",IF(B14<0.85,"Ocupação saudável: trabalhe ticket e frequência","Agenda quase cheia: hora de reajustar preço ou contratar")))
A23: ACOMPANHAMENTO MENSAL
A24: Mês | B24: Faturamento | C24: Atendimentos | D24: Ticket médio | E24: Clientes novas | F24: Novas que voltaram em 60 dias | G24: Taxa de retorno | H24: Ocupação
A25: Jan | D25: =IF(OR(C25="",C25=0),"",B25/C25) | G25: =IF(OR(E25="",E25=0),"",F25/E25)
A26: Fev | D26: =IF(OR(C26="",C26=0),"",B26/C26) | G26: =IF(OR(E26="",E26=0),"",F26/E26)
A27: Mar | D27: =IF(OR(C27="",C27=0),"",B27/C27) | G27: =IF(OR(E27="",E27=0),"",F27/E27)
A28: Abr | D28: =IF(OR(C28="",C28=0),"",B28/C28) | G28: =IF(OR(E28="",E28=0),"",F28/E28)
A29: Mai | D29: =IF(OR(C29="",C29=0),"",B29/C29) | G29: =IF(OR(E29="",E29=0),"",F29/E29)
A30: Jun | D30: =IF(OR(C30="",C30=0),"",B30/C30) | G30: =IF(OR(E30="",E30=0),"",F30/E30)
A31: Jul | D31: =IF(OR(C31="",C31=0),"",B31/C31) | G31: =IF(OR(E31="",E31=0),"",F31/E31)
A32: Ago | D32: =IF(OR(C32="",C32=0),"",B32/C32) | G32: =IF(OR(E32="",E32=0),"",F32/E32)
A33: Set | D33: =IF(OR(C33="",C33=0),"",B33/C33) | G33: =IF(OR(E33="",E33=0),"",F33/E33)
A34: Out | D34: =IF(OR(C34="",C34=0),"",B34/C34) | G34: =IF(OR(E34="",E34=0),"",F34/E34)
A35: Nov | D35: =IF(OR(C35="",C35=0),"",B35/C35) | G35: =IF(OR(E35="",E35=0),"",F35/E35)
A36: Dez | D36: =IF(OR(C36="",C36=0),"",B36/C36) | G36: =IF(OR(E36="",E36=0),"",F36/E36)
A38: Taxa de retorno abaixo de 40% (em vermelho): o problema é experiência ou falta de lembrete, não marketing.

Sheet Calendário 30 dias
A1: Calendário de conteúdo: 30 dias
A2: Um tipo de conteúdo por dia. Gere a semana inteira no domingo com o Prompt 12.
A4: Dia | B4: Semana / foco | C4: Dia da semana | D4: Tipo | E4: Ideia de post | F4: Prompt | G4: Feito?
A5: 1 | B5: 1 · Apresentar o salão | C5: Seg | D5: Atração | E5: Dica rápida de cuidado em casa | F5: 6
A6: 2 | B6: 1 · Apresentar o salão | C6: Ter | D6: Venda | E6: Horários livres da semana + link do WhatsApp | F6: 15
A7: 3 | B7: 1 · Apresentar o salão | C7: Qua | D7: Prova | E7: Antes e depois do carro-chefe | F7: 7
A8: 4 | B8: 1 · Apresentar o salão | C8: Qui | D8: Prova | E8: Depoimento de cliente | F8: 11
A9: 5 | B9: 1 · Apresentar o salão | C9: Sex | D9: Atração | E9: Reels de transformação | F9: 9
A10: 6 | B10: 1 · Apresentar o salão | C10: Sáb | D10: Conexão | E10: Bastidor: um dia no salão / equipe | F10: 8
A11: 7 | B11: 1 · Apresentar o salão | C11: Dom | D11: Descanso | E11: Story leve + gerar os posts da semana | F11: 12
A12: 8 | B12: 2 · Carro-chefe | C12: Seg | D12: Atração | E12: Dica rápida de cuidado em casa | F12: 6
A13: 9 | B13: 2 · Carro-chefe | C13: Ter | D13: Venda | E13: Horários livres da semana + link do WhatsApp | F13: 15
A14: 10 | B14: 2 · Carro-chefe | C14: Qua | D14: Prova | E14: Antes e depois do carro-chefe | F14: 7
A15: 11 | B15: 2 · Carro-chefe | C15: Qui | D15: Prova | E15: Depoimento de cliente | F15: 11
A16: 12 | B16: 2 · Carro-chefe | C16: Sex | D16: Atração | E16: Reels de transformação | F16: 9
... A34: 30 | B34: 5 · Revisão | C34: Ter | D34: Venda | E34: Horários livres da semana + link do WhatsApp | F34: 15

Sheet Campanhas do ano
A1: Campanhas do ano
A2: Comece a divulgar 3 a 4 semanas antes. Use o Prompt 41 para montar cada campanha.
A4: Mês | B4: Data / período | C4: Oportunidade | D4: Ideia de campanha | E4: Começar a divulgar em | F4: Minha oferta | G4: Resultado
A5: Janeiro | B5: Todo o mês | C5: Verão e volta das festas | D5: Pacote de hidratação pós-praia
A6: Fevereiro | B6: Carnaval | C6: Carnaval | D6: Tranças, glitter, unhas coloridas, horário estendido
A7: Março | B7: 08/03 | C7: Dia da Mulher | D7: Dia de beleza para presentear, sorteio entre clientes
A8: Abril | B8: Páscoa | C8: Páscoa | D8: Mimo de chocolate no atendimento
A9: Maio | B9: 2º domingo | C9: Dia das Mães | D9: Vale-presente e dia de mãe e filha
A10: Junho | B10: 12/06 | C10: Dia dos Namorados | D10: Combo pronta para o encontro
A11: Julho | B11: Férias | C11: Férias escolares | D11: Horários para mães, serviços infantis
A12: Agosto | B12: 2º domingo | C12: Dia dos Pais | D12: Corte e barba, vale-presente
A13: Setembro | B13: 15/09 | C13: Dia do Cliente | D13: Agradecimento às clientes fiéis
A14: Outubro | B14: Todo o mês | C14: Outubro Rosa / lista VIP Black Friday | D14: Ação solidária e abertura da lista VIP
A15: Novembro | B15: Última sexta | C15: Black Friday | D15: Combos e vale-presente com bônus (Prompt 42)
A16: Dezembro | B16: Festas | C16: Natal, Réveillon, formaturas | D16: Agenda antecipada e pacote das festas

Sheet Vales e Pacotes
A1: Vale-presentes e pacotes vendidos
A2: A validade é calculada sozinha (90 dias). Mude o prazo na célula H2. | G2: Validade (dias): | H2: 90
A4: Código | B4: Tipo | C4: Comprador(a) | D4: Para quem | E4: Valor pago | F4: Valor de uso | G4: Data da venda | H4: Válido até | I4: Já usado? | J4: Situação | L4: Total vendido | M4: =SUM(E5:E104)
A5: =IF(C5="","","V"&TEXT(ROW()-4,"000")) | H5: =IF(G5="","",G5+$H$2) | J5: =IF(G5="","",IF(I5="Sim","Usado",IF(TODAY()>H5,"Vencido",IF(H5-TODAY()<=15,"Vence em breve","Ativo")))) | L5: Ativos (valor de uso) | M5: =SUMIF(J5:J104,"Ativo",F5:F104)+SUMIF(J5:J104,"Vence em breve",F5:F104)
A6: =IF(C6="","","V"&TEXT(ROW()-4,"000")) | H6: =IF(G6="","",G6+$H$2) | J6: =IF(G6="","",IF(I6="Sim","Usado",IF(TODAY()>H6,"Vencido",IF(H6-TODAY()<=15,"Vence em breve","Ativo")))) | L6: Vencem em breve | M6: =COUNTIF(J5:J104,"Vence em breve")
A7: =IF(C7="","","V"&TEXT(ROW()-4,"000")) | H7: =IF(G7="","",G7+$H$2) | J7: =IF(G7="","",IF(I7="Sim","Usado",IF(TODAY()>H7,"Vencido",IF(H7-TODAY()<=15,"Vence em breve","Ativo"))))
A8: =IF(C8="","","V"&TEXT(ROW()-4,"000")) | H8: =IF(G8="","",G8+$H$2) | J8: =IF(G8="","",IF(I8="Sim","Usado",IF(TODAY()>H8,"Vencido",IF(H8-TODAY()<=15,"Vence em breve","Ativo"))))
A9: =IF(C9="","","V"&TEXT(ROW()-4,"000")) | H9: =IF(G9="","",G9+$H$2) | J9: =IF(G9="","",IF(I9="Sim","Usado",IF(TODAY()>H9,"Vencido",IF(H9-TODAY()<=15,"Vence em breve","Ativo"))))
A10: =IF(C10="","","V"&TEXT(ROW()-4,"000")) | H10: =IF(G10="","",G10+$H$2) | J10: =IF(G10="","",IF(I10="Sim","Usado",IF(TODAY()>H10,"Vencido",IF(H10-TODAY()<=15,"Vence em breve","Ativo"))))
A11: =IF(C11="","","V"&TEXT(ROW()-4,"000")) | H11: =IF(G11="","",G11+$H$2) | J11: =IF(G11="","",IF(I11="Sim","Usado",IF(TODAY()>H11,"Vencido",IF(H11-TODAY()<=15,"Vence em breve","Ativo"))))
A12: =IF(C12="","","V"&TEXT(ROW()-4,"000")) | H12: =IF(G12="","",G12+$H$2) | J12: =IF(G12="","",IF(I12="Sim","Usado",IF(TODAY()>H12,"Vencido",IF(H12-TODAY()<=15,"Vence em breve","Ativo"))))
A13: =IF(C13="","","V"&TEXT(ROW()-4,"000")) | H13: =IF(G13="","",G13+$H$2) | J13: =IF(G13="","",IF(I13="Sim","Usado",IF(TODAY()>H13,"Vencido",IF(H13-TODAY()<=15,"Vence em breve","Ativo"))))
A14: =IF(C14="","","V"&TEXT(ROW()-4,"000")) | H14: =IF(G14="","",G14+$H$2) | J14: =IF(G14="","",IF(I14="Sim","Usado",IF(TODAY()>H14,"Vencido",IF(H14-TODAY()<=15,"Vence em breve","Ativo"))))
A15: =IF(C15="","","V"&TEXT(ROW()-4,"000")) | H15: =IF(G15="","",G15+$H$2) | J15: =IF(G15="","",IF(I15="Sim","Usado",IF(TODAY()>H15,"Vencido",IF(H15-TODAY()<=15,"Vence em breve","Ativo"))))
A16: =IF(C16="","","V"&TEXT(ROW()-4,"000")) | H16: =IF(G16="","",G16+$H$2) | J16: =IF(G16="","",IF(I16="Sim","Usado",IF(TODAY()>H16,"Vencido",IF(H16-TODAY()<=15,"Vence em breve","Ativo"))))
A17: =IF(C17="","","V"&TEXT(ROW()-4,"000")) | H17: =IF(G17="","",G17+$H$2) | J17: =IF(G17="","",IF(I17="Sim","Usado",IF(TODAY()>H17,"Vencido",IF(H17-TODAY()<=15,"Vence em breve","Ativo"))))
A18: =IF(C18="","","V"&TEXT(ROW()-4,"000")) | H18: =IF(G18="","",G18+$H$2) | J18: =IF(G18="","",IF(I18="Sim","Usado",IF(TODAY()>H18,"Vencido",IF(H18-TODAY()<=15,"Vence em breve","Ativo"))))
... A104: =IF(C104="","","V"&TEXT(ROW()-4,"000")) | H104: =IF(G104="","",G104+$H$2) | J104: =IF(G104="","",IF(I104="Sim","Usado",IF(TODAY()>H104,"Vencido",IF(H104-TODAY()<=15,"Vence em breve","Ativo"))))
