Workbook

Sheet Como usar
A1: Contas em Dia com IA — Planilha
A2: Preencha só as células amarelas. O resto é calculado sozinho.
A4: 1. Aba 'Orçamento do Mês': coloque suas entradas e seus gastos (use o Prompt 1 do guia para organizar o extrato).
A5: 2. Aba 'Minhas Dívidas': liste TODAS as dívidas, com o saldo de hoje, os juros ao mês e a parcela.
A6: 3. A mesma aba mostra a ordem de pagamento pelos métodos Avalanche (juros maiores primeiro) e Bola de Neve (menor dívida primeiro).
A7: 4. Aba 'Plano': veja quanto sobra por mês e qual dívida atacar primeiro.
A8: 5. Copie a tabela de dívidas e cole no Prompt 6 do guia para a IA montar o plano mês a mês.
A9: 6. Atualize uma vez por mês.
A11: Segurança: não coloque nesta planilha nem na IA seu CPF, senhas ou número do cartão.
A12: Esta planilha é uma ferramenta educativa. As estimativas de prazo não consideram juros e servem só de referência.

Sheet Orçamento do Mês
A1: Orçamento do Mês
A2: Mês de referência:
A4: Tipo | B4: Descrição | C4: Valor (R$)
A5: Entrada | B5: Salário / renda principal
A6: Entrada | B6: Renda extra
A7: Entrada | B7: Outros
A8: Essencial | B8: Aluguel ou prestação
A9: Essencial | B9: Condomínio
A10: Essencial | B10: Água
A11: Essencial | B11: Luz
A12: Essencial | B12: Gás
A13: Essencial | B13: Internet e celular
A14: Essencial | B14: Mercado
A15: Essencial | B15: Transporte
A16: Essencial | B16: Saúde e remédios
... A22: Pessoal | B22: Outros
A23: Dívidas | B23: Parcelas de dívidas (total da aba Dívidas) | C23: ='Minhas Dívidas'!F18
B25: Total de entradas | C25: =SUMIF(A5:A23,"Entrada",C5:C23)
B26: Total essencial | C26: =SUMIF(A5:A23,"Essencial",C5:C23)
B27: Total pessoal | C27: =SUMIF(A5:A23,"Pessoal",C5:C23)
B28: Total de parcelas de dívidas | C28: =SUMIF(A5:A23,"Dívidas",C5:C23)
B29: SOBRA DO MÊS | C29: =C25-C26-C27-C28
B30: % da renda em essenciais | C30: =IF(C25=0,0,C26/C25)
B31: % da renda em dívidas | C31: =IF(C25=0,0,C28/C25)

Sheet Minhas Dívidas
A1: Minhas Dívidas
A2: Liste todas. Juros ao mês: ex. 12% no rotativo do cartão = 12
A4: Credor | B4: Tipo | C4: Saldo devedor hoje (R$) | D4: Juros ao mês (%) | E4: Atrasada? (Sim/Não) | F4: Parcela mínima (R$) | G4: Ordem Avalanche (juros maiores 1º) | H4: Ordem Bola de Neve (menor saldo 1º)
A5: Exemplo: Banco X | B5: Cartão - rotativo | C5: 1500 | D5: 12 | E5: Não | F5: 225 | G5: =IF(C5>0,COUNTIFS($C$5:$C$16,">0",$D$5:$D$16,">"&D5)+COUNTIFS($C$5:C5,">0",$D$5:D5,D5),"") | H5: =IF(C5>0,COUNTIFS($C$5:$C$16,">0",$C$5:$C$16,"<"&C5)+COUNTIFS($C$5:C5,C5),"")
G6: =IF(C6>0,COUNTIFS($C$5:$C$16,">0",$D$5:$D$16,">"&D6)+COUNTIFS($C$5:C6,">0",$D$5:D6,D6),"") | H6: =IF(C6>0,COUNTIFS($C$5:$C$16,">0",$C$5:$C$16,"<"&C6)+COUNTIFS($C$5:C6,C6),"")
G7: =IF(C7>0,COUNTIFS($C$5:$C$16,">0",$D$5:$D$16,">"&D7)+COUNTIFS($C$5:C7,">0",$D$5:D7,D7),"") | H7: =IF(C7>0,COUNTIFS($C$5:$C$16,">0",$C$5:$C$16,"<"&C7)+COUNTIFS($C$5:C7,C7),"")
G8: =IF(C8>0,COUNTIFS($C$5:$C$16,">0",$D$5:$D$16,">"&D8)+COUNTIFS($C$5:C8,">0",$D$5:D8,D8),"") | H8: =IF(C8>0,COUNTIFS($C$5:$C$16,">0",$C$5:$C$16,"<"&C8)+COUNTIFS($C$5:C8,C8),"")
G9: =IF(C9>0,COUNTIFS($C$5:$C$16,">0",$D$5:$D$16,">"&D9)+COUNTIFS($C$5:C9,">0",$D$5:D9,D9),"") | H9: =IF(C9>0,COUNTIFS($C$5:$C$16,">0",$C$5:$C$16,"<"&C9)+COUNTIFS($C$5:C9,C9),"")
G10: =IF(C10>0,COUNTIFS($C$5:$C$16,">0",$D$5:$D$16,">"&D10)+COUNTIFS($C$5:C10,">0",$D$5:D10,D10),"") | H10: =IF(C10>0,COUNTIFS($C$5:$C$16,">0",$C$5:$C$16,"<"&C10)+COUNTIFS($C$5:C10,C10),"")
G11: =IF(C11>0,COUNTIFS($C$5:$C$16,">0",$D$5:$D$16,">"&D11)+COUNTIFS($C$5:C11,">0",$D$5:D11,D11),"") | H11: =IF(C11>0,COUNTIFS($C$5:$C$16,">0",$C$5:$C$16,"<"&C11)+COUNTIFS($C$5:C11,C11),"")
G12: =IF(C12>0,COUNTIFS($C$5:$C$16,">0",$D$5:$D$16,">"&D12)+COUNTIFS($C$5:C12,">0",$D$5:D12,D12),"") | H12: =IF(C12>0,COUNTIFS($C$5:$C$16,">0",$C$5:$C$16,"<"&C12)+COUNTIFS($C$5:C12,C12),"")
G13: =IF(C13>0,COUNTIFS($C$5:$C$16,">0",$D$5:$D$16,">"&D13)+COUNTIFS($C$5:C13,">0",$D$5:D13,D13),"") | H13: =IF(C13>0,COUNTIFS($C$5:$C$16,">0",$C$5:$C$16,"<"&C13)+COUNTIFS($C$5:C13,C13),"")
G14: =IF(C14>0,COUNTIFS($C$5:$C$16,">0",$D$5:$D$16,">"&D14)+COUNTIFS($C$5:C14,">0",$D$5:D14,D14),"") | H14: =IF(C14>0,COUNTIFS($C$5:$C$16,">0",$C$5:$C$16,"<"&C14)+COUNTIFS($C$5:C14,C14),"")
G15: =IF(C15>0,COUNTIFS($C$5:$C$16,">0",$D$5:$D$16,">"&D15)+COUNTIFS($C$5:C15,">0",$D$5:D15,D15),"") | H15: =IF(C15>0,COUNTIFS($C$5:$C$16,">0",$C$5:$C$16,"<"&C15)+COUNTIFS($C$5:C15,C15),"")
G16: =IF(C16>0,COUNTIFS($C$5:$C$16,">0",$D$5:$D$16,">"&D16)+COUNTIFS($C$5:C16,">0",$D$5:D16,D16),"") | H16: =IF(C16>0,COUNTIFS($C$5:$C$16,">0",$C$5:$C$16,"<"&C16)+COUNTIFS($C$5:C16,C16),"")
B18: TOTAIS | C18: =SUM(C5:C16) | F18: =SUM(F5:F16)
B19: Maior juros ao mês | D19: =MAX(D5:D16)
A21: Apague a linha de exemplo quando preencher as suas dívidas.

Sheet Plano
A1: Plano de Quitação
A2: Resumo automático a partir das outras abas.
B4: Sobra do mês (aba Orçamento) | C4: ='Orçamento do Mês'!C29
B5: Dinheiro extra que vou colocar nas dívidas por mês
B6: Total que devo hoje | C6: ='Minhas Dívidas'!C18
B7: Soma das parcelas mínimas | C7: ='Minhas Dívidas'!F18
B9: AVALANCHE: atacar primeiro | C9: =IFERROR(INDEX('Minhas Dívidas'!$A$5:$A$16,MATCH(1,'Minhas Dívidas'!$G$5:$G$16,0)),"—")
B10: BOLA DE NEVE: atacar primeiro | C10: =IFERROR(INDEX('Minhas Dívidas'!$A$5:$A$16,MATCH(1,'Minhas Dívidas'!$H$5:$H$16,0)),"—")
B12: Meses estimados para quitar tudo (sem contar juros) | C12: =IF((C7+C5)<=0,"Sem sobra: revise o orçamento",ROUNDUP(C6/(C7+C5),0))
B15: Atenção: com juros, o prazo real é maior. Use o Prompt 6 do guia para a IA calcular o plano mês a mês.
B16: Se a sobra do mês estiver negativa, o primeiro passo é cortar gastos (Prompt 2) ou negociar parcelas menores (Prompt 7).
