Workbook

Sheet Instruções
A1: Planilha de Gestão do Freela — Kit Freela Digital com IA
A3: Como usar:
A4: 1. Precificação: preencha as células AMARELAS com seus custos, pró-labore e horas. O valor hora mínimo é calculado automaticamente.
A5: 2. Pacotes: informe as horas estimadas de cada pacote. O preço sugerido considera seu valor hora, margem e impostos/taxas.
A6: 3. Clientes (CRM): registre cada potencial cliente, a etapa do funil e a data do próximo contato.
A7: 4. Caixa: lance entradas e saídas do mês. O resumo mostra o saldo e o total por categoria.
A9: Legenda: células amarelas = você preenche · células verdes = resultado automático.

Sheet Precificação
A1: Precificação — valor hora mínimo
A3: Custos fixos mensais | B3: Valor
A4: Internet | B4: 100
A5: Energia (parte do trabalho) | B5: 60
A6: Ferramentas de IA | B6: 100
A7: Canva / design | B7: 35
A8: Celular | B8: 50
A9: DAS do MEI | B9: 80
A10: Outros | B10: 0
A11: Total de custos fixos | B11: =SUM(B4:B10)
A13: Parâmetros
A14: Pró-labore desejado (R$/mês) | B14: 3000
A15: Horas de trabalho por dia | B15: 6
A16: Dias de trabalho por mês | B16: 22
A17: % do tempo faturável (produção para clientes) | B17: 0.65
A18: Margem de lucro desejada | B18: 0.3
A19: Impostos e taxas sobre o preço | B19: 0.06
A21: Resultados
A22: Horas faturáveis por mês | B22: =B15*B16*B17
A23: VALOR HORA MÍNIMO | B23: =IF(B22>0,(B11+B14)/B22,0)
A24: Valor hora com margem e impostos | B24: =B23*(1+B18)/(1-B19)
A25: Faturamento necessário no mês | B25: =B24*B22

Sheet Pacotes
A1: Preço dos pacotes
A2: Preencha as horas estimadas por mês/projeto. O preço usa os parâmetros da aba Precificação.
A4: Pacote | B4: Entregáveis (resumo) | C4: Horas estimadas | D4: Custo (horas × valor hora) | E4: Preço sugerido | F4: Preço que vou cobrar | G4: Lucro estimado
A5: Oferta de entrada | B5: Diagnóstico + 5 artes | C5: 4 | D5: =C5*Precificação!B23 | E5: =ROUNDUP(C5*Precificação!B23*(1+Precificação!B18)/(1-Precificação!B19),-1)-0.1 | F5: =E5 | G5: =F5*(1-Precificação!B19)-D5
A6: Essencial | B6: 8 posts/mês + legendas | C6: 10 | D6: =C6*Precificação!B23 | E6: =ROUNDUP(C6*Precificação!B23*(1+Precificação!B18)/(1-Precificação!B19),-1)-0.1 | F6: =E6 | G6: =F6*(1-Precificação!B19)-D6
A7: Profissional | B7: 12 posts + stories 3x/sem + 2 reels + relatório | C7: 18 | D7: =C7*Precificação!B23 | E7: =ROUNDUP(C7*Precificação!B23*(1+Precificação!B18)/(1-Precificação!B19),-1)-0.1 | F7: =E7 | G7: =F7*(1-Precificação!B19)-D7
A8: Completo | B8: 16 posts + stories 5x/sem + 4 reels + reunião | C8: 28 | D8: =C8*Precificação!B23 | E8: =ROUNDUP(C8*Precificação!B23*(1+Precificação!B18)/(1-Precificação!B19),-1)-0.1 | F8: =E8 | G8: =F8*(1-Precificação!B19)-D8

Sheet Clientes (CRM)
A1: Clientes e prospecção
A2: Etapas: Lead → Abordado → Respondeu → Diagnóstico → Proposta enviada → Fechado → Perdido
A4: Empresa | B4: Contato | C4: Nicho | D4: Canal | E4: Etapa | F4: Último contato | G4: Próximo contato | H4: Pacote | I4: Valor mensal | J4: Observações | K4: Atrasado? | M4: Resumo do funil | N4: Qtd.
A5: Clínica Sorriso (exemplo) | B5: Dra. Ana | C5: Odontologia | D5: Instagram | E5: Proposta enviada | F5: 46296 | G5: 46299 | H5: Profissional | I5: 890 | J5: Pediu para retornar na sexta | K5: =IF(AND(G5<>"",E5<>"Fechado",E5<>"Perdido",G5<TODAY()),"SIM","") | M5: Lead | N5: =COUNTIF($E$5:$E$300,M5)
K6: =IF(AND(G6<>"",E6<>"Fechado",E6<>"Perdido",G6<TODAY()),"SIM","") | M6: Abordado | N6: =COUNTIF($E$5:$E$300,M6)
K7: =IF(AND(G7<>"",E7<>"Fechado",E7<>"Perdido",G7<TODAY()),"SIM","") | M7: Respondeu | N7: =COUNTIF($E$5:$E$300,M7)
K8: =IF(AND(G8<>"",E8<>"Fechado",E8<>"Perdido",G8<TODAY()),"SIM","") | M8: Diagnóstico | N8: =COUNTIF($E$5:$E$300,M8)
K9: =IF(AND(G9<>"",E9<>"Fechado",E9<>"Perdido",G9<TODAY()),"SIM","") | M9: Proposta enviada | N9: =COUNTIF($E$5:$E$300,M9)
K10: =IF(AND(G10<>"",E10<>"Fechado",E10<>"Perdido",G10<TODAY()),"SIM","") | M10: Fechado | N10: =COUNTIF($E$5:$E$300,M10)
K11: =IF(AND(G11<>"",E11<>"Fechado",E11<>"Perdido",G11<TODAY()),"SIM","") | M11: Perdido | N11: =COUNTIF($E$5:$E$300,M11)
K12: =IF(AND(G12<>"",E12<>"Fechado",E12<>"Perdido",G12<TODAY()),"SIM","")
K13: =IF(AND(G13<>"",E13<>"Fechado",E13<>"Perdido",G13<TODAY()),"SIM","") | M13: Receita recorrente (fechados) | N13: =SUMIF($E$5:$E$300,"Fechado",$I$5:$I$300)
K14: =IF(AND(G14<>"",E14<>"Fechado",E14<>"Perdido",G14<TODAY()),"SIM","")
K15: =IF(AND(G15<>"",E15<>"Fechado",E15<>"Perdido",G15<TODAY()),"SIM","")
K16: =IF(AND(G16<>"",E16<>"Fechado",E16<>"Perdido",G16<TODAY()),"SIM","")
K17: =IF(AND(G17<>"",E17<>"Fechado",E17<>"Perdido",G17<TODAY()),"SIM","")
K18: =IF(AND(G18<>"",E18<>"Fechado",E18<>"Perdido",G18<TODAY()),"SIM","")
K19: =IF(AND(G19<>"",E19<>"Fechado",E19<>"Perdido",G19<TODAY()),"SIM","")
K20: =IF(AND(G20<>"",E20<>"Fechado",E20<>"Perdido",G20<TODAY()),"SIM","")
K21: =IF(AND(G21<>"",E21<>"Fechado",E21<>"Perdido",G21<TODAY()),"SIM","")
K22: =IF(AND(G22<>"",E22<>"Fechado",E22<>"Perdido",G22<TODAY()),"SIM","")
K23: =IF(AND(G23<>"",E23<>"Fechado",E23<>"Perdido",G23<TODAY()),"SIM","")
K24: =IF(AND(G24<>"",E24<>"Fechado",E24<>"Perdido",G24<TODAY()),"SIM","")
K25: =IF(AND(G25<>"",E25<>"Fechado",E25<>"Perdido",G25<TODAY()),"SIM","")
... K300: =IF(AND(G300<>"",E300<>"Fechado",E300<>"Perdido",G300<TODAY()),"SIM","")

Sheet Caixa
A1: Caixa do mês
A4: Data | B4: Descrição | C4: Tipo | D4: Categoria | E4: Valor | G4: Resumo | H4: Valor
A5: 46300 | B5: Clínica Sorriso — mensalidade (exemplo) | C5: Entrada | D5: Cliente recorrente | E5: 890 | G5: Entradas | H5: =SUMIF($C$5:$C$400,"Entrada",$E$5:$E$400)
A6: 46301 | B6: Assinatura ferramenta de IA (exemplo) | C6: Saída | D6: Ferramentas | E6: 100 | G6: Saídas | H6: =SUMIF($C$5:$C$400,"Saída",$E$5:$E$400)
G7: Saldo | H7: =H5-H6
G9: Por categoria | H9: Valor
G10: Cliente recorrente | H10: =SUMIF($D$5:$D$400,G10,$E$5:$E$400)
G11: Projeto pontual | H11: =SUMIF($D$5:$D$400,G11,$E$5:$E$400)
G12: Ferramentas | H12: =SUMIF($D$5:$D$400,G12,$E$5:$E$400)
G13: Impostos | H13: =SUMIF($D$5:$D$400,G13,$E$5:$E$400)
G14: Marketing | H14: =SUMIF($D$5:$D$400,G14,$E$5:$E$400)
G15: Equipamento | H15: =SUMIF($D$5:$D$400,G15,$E$5:$E$400)
G16: Pró-labore | H16: =SUMIF($D$5:$D$400,G16,$E$5:$E$400)
G17: Outros | H17: =SUMIF($D$5:$D$400,G17,$E$5:$E$400)
