Workbook

Sheet Sheet
A1: Planilhas do Corretor
A2: Preencha só as células AMARELAS. As células coloridas são calculadas sozinhas.
A4: COMO USAR
A5: 1. 'Meta Reversa': diga quanto quer ganhar e suas taxas de conversão. Descubra quantos leads, atendimentos e visitas precisa por semana.
A6: 2. 'Funil': cadastre cada lead. Na coluna Etapa use 1=Lead, 2=Atendimento, 3=Visita, 4=Proposta, 5=Venda. Atualize o 'Último contato'.
A7: A coluna 'Próximo contato' segue a cadência de acompanhamento. Vermelho = atrasado. Amarelo = hoje.
A8: 3. 'Painel': mostra suas taxas reais de conversão e onde está o gargalo. Depois de 2 ou 3 meses, use essas taxas na Meta Reversa.
A9: 4. 'ACM': análise comparativa de mercado. Coloque imóveis parecidos e veja o preço por m² e a faixa de preço sugerida.
A10: 5. 'Captações': controle prazos de exclusividade e imóveis que precisam de revisão de preço.
A11: 6. 'Comissões': o que você já recebeu e o que ainda vai receber.
A12: 7. 'Simuladores': custos da compra, SAC x Price e rentabilidade de aluguel. São ESTIMATIVAS: os valores oficiais vêm do banco, prefeitura e cartório.
A13: 8. 'Calendário 30 dias': o que postar em cada dia, com o prompt da Biblioteca.
... A16: Os valores já preenchidos são EXEMPLOS: troque pelos seus.

Sheet Meta Reversa
A1: Meta reversa
A2: Comece pelo quanto quer ganhar e descubra o que precisa fazer por semana.
A4: Quanto quero ganhar por mês (R$) | B4: 10000
A5: Ticket médio dos imóveis (R$) | B5: 500000
A6: Comissão total da venda (%) | B6: 0.06
A7: Minha parte da comissão (%) | B7: 0.5
A8: Lead → atendimento (%) | B8: 0.5 | C8: ← taxas de referência para começar. Use as suas reais do 'Painel'.
A9: Atendimento → visita (%) | B9: 0.33
A10: Visita → proposta (%) | B10: 0.2
A11: Proposta → venda (%) | B11: 0.25
A13: Resultado | B13: Por mês | C13: Por semana
A14: Minha comissão por venda | B14: =B5*B6*B7
A15: Vendas necessárias | B15: =IF(B14=0,0,B4/B14) | C15: =B15/4.3
A16: Propostas necessárias | B16: =IF(B11=0,0,B15/B11) | C16: =B16/4.3
A17: Visitas necessárias | B17: =IF(B10=0,0,B16/B10) | C17: =B17/4.3
A18: Atendimentos necessários | B18: =IF(B9=0,0,B17/B9) | C18: =B18/4.3
A19: Leads necessários | B19: =IF(B8=0,0,B18/B8) | C19: =B19/4.3
A21: Leitura: 0,67 venda por mês = 2 vendas a cada 3 meses. Se os leads necessários forem muitos, melhore a taxa do gargalo antes de buscar mais leads.

Sheet Funil
A1: Funil de leads | M1: Cadência (dias até o próximo contato)
A2: Etapa: 1=Lead 2=Atendimento 3=Visita 4=Proposta 5=Venda. Marque 'Perdido' = Sim quando o lead desistir. | M2: Etapa → dias
M3: 1 | N3: 1
M4: 2 | N4: 3
M5: 3 | N5: 2
M6: 4 | N6: 1
M7: 5 | N7: 30
A9: Entrada | B9: Nome | C9: WhatsApp | D9: Origem | E9: Finalidade | F9: Interesse (tipo, bairro, faixa) | G9: Etapa (1-5) | H9: Etapa | I9: Último contato | J9: Próximo contato | K9: Situação | L9: Perdido? | M9: Motivo da perda / notas
A10: =TODAY()-12 | B10: Rafael (exemplo) | D10: Portal | E10: Morar | F10: 2 dorms Tatuapé até 550 mil | G10: 3 | H10: =IF(G10="","",CHOOSE(G10,"Lead","Atendimento","Visita","Proposta","Venda")) | I10: =TODAY()-5 | J10: =IF(OR(G10="",I10="",L10="Sim"),"",I10+VLOOKUP(G10,$M$3:$N$7,2,FALSE)) | K10: =IF(L10="Sim","Perdido",IF(J10="","",IF(J10<TODAY(),"ATRASADO",IF(J10=TODAY(),"Hoje","Em dia")))) | L10: Não
A11: =TODAY()-3 | B11: Juliana (exemplo) | D11: Instagram | E11: Morar | F11: 3 dorms Mooca | G11: 2 | H11: =IF(G11="","",CHOOSE(G11,"Lead","Atendimento","Visita","Proposta","Venda")) | I11: =TODAY()-1 | J11: =IF(OR(G11="",I11="",L11="Sim"),"",I11+VLOOKUP(G11,$M$3:$N$7,2,FALSE)) | K11: =IF(L11="Sim","Perdido",IF(J11="","",IF(J11<TODAY(),"ATRASADO",IF(J11=TODAY(),"Hoje","Em dia")))) | L11: Não
A12: =TODAY()-20 | B12: Marcos (exemplo) | D12: Indicação | E12: Investir | F12: Studio perto do metrô | G12: 4 | H12: =IF(G12="","",CHOOSE(G12,"Lead","Atendimento","Visita","Proposta","Venda")) | I12: =TODAY()-1 | J12: =IF(OR(G12="",I12="",L12="Sim"),"",I12+VLOOKUP(G12,$M$3:$N$7,2,FALSE)) | K12: =IF(L12="Sim","Perdido",IF(J12="","",IF(J12<TODAY(),"ATRASADO",IF(J12=TODAY(),"Hoje","Em dia")))) | L12: Não
H13: =IF(G13="","",CHOOSE(G13,"Lead","Atendimento","Visita","Proposta","Venda")) | J13: =IF(OR(G13="",I13="",L13="Sim"),"",I13+VLOOKUP(G13,$M$3:$N$7,2,FALSE)) | K13: =IF(L13="Sim","Perdido",IF(J13="","",IF(J13<TODAY(),"ATRASADO",IF(J13=TODAY(),"Hoje","Em dia"))))
H14: =IF(G14="","",CHOOSE(G14,"Lead","Atendimento","Visita","Proposta","Venda")) | J14: =IF(OR(G14="",I14="",L14="Sim"),"",I14+VLOOKUP(G14,$M$3:$N$7,2,FALSE)) | K14: =IF(L14="Sim","Perdido",IF(J14="","",IF(J14<TODAY(),"ATRASADO",IF(J14=TODAY(),"Hoje","Em dia"))))
H15: =IF(G15="","",CHOOSE(G15,"Lead","Atendimento","Visita","Proposta","Venda")) | J15: =IF(OR(G15="",I15="",L15="Sim"),"",I15+VLOOKUP(G15,$M$3:$N$7,2,FALSE)) | K15: =IF(L15="Sim","Perdido",IF(J15="","",IF(J15<TODAY(),"ATRASADO",IF(J15=TODAY(),"Hoje","Em dia"))))
H16: =IF(G16="","",CHOOSE(G16,"Lead","Atendimento","Visita","Proposta","Venda")) | J16: =IF(OR(G16="",I16="",L16="Sim"),"",I16+VLOOKUP(G16,$M$3:$N$7,2,FALSE)) | K16: =IF(L16="Sim","Perdido",IF(J16="","",IF(J16<TODAY(),"ATRASADO",IF(J16=TODAY(),"Hoje","Em dia"))))
H17: =IF(G17="","",CHOOSE(G17,"Lead","Atendimento","Visita","Proposta","Venda")) | J17: =IF(OR(G17="",I17="",L17="Sim"),"",I17+VLOOKUP(G17,$M$3:$N$7,2,FALSE)) | K17: =IF(L17="Sim","Perdido",IF(J17="","",IF(J17<TODAY(),"ATRASADO",IF(J17=TODAY(),"Hoje","Em dia"))))
H18: =IF(G18="","",CHOOSE(G18,"Lead","Atendimento","Visita","Proposta","Venda")) | J18: =IF(OR(G18="",I18="",L18="Sim"),"",I18+VLOOKUP(G18,$M$3:$N$7,2,FALSE)) | K18: =IF(L18="Sim","Perdido",IF(J18="","",IF(J18<TODAY(),"ATRASADO",IF(J18=TODAY(),"Hoje","Em dia"))))
H19: =IF(G19="","",CHOOSE(G19,"Lead","Atendimento","Visita","Proposta","Venda")) | J19: =IF(OR(G19="",I19="",L19="Sim"),"",I19+VLOOKUP(G19,$M$3:$N$7,2,FALSE)) | K19: =IF(L19="Sim","Perdido",IF(J19="","",IF(J19<TODAY(),"ATRASADO",IF(J19=TODAY(),"Hoje","Em dia"))))
H20: =IF(G20="","",CHOOSE(G20,"Lead","Atendimento","Visita","Proposta","Venda")) | J20: =IF(OR(G20="",I20="",L20="Sim"),"",I20+VLOOKUP(G20,$M$3:$N$7,2,FALSE)) | K20: =IF(L20="Sim","Perdido",IF(J20="","",IF(J20<TODAY(),"ATRASADO",IF(J20=TODAY(),"Hoje","Em dia"))))
H21: =IF(G21="","",CHOOSE(G21,"Lead","Atendimento","Visita","Proposta","Venda")) | J21: =IF(OR(G21="",I21="",L21="Sim"),"",I21+VLOOKUP(G21,$M$3:$N$7,2,FALSE)) | K21: =IF(L21="Sim","Perdido",IF(J21="","",IF(J21<TODAY(),"ATRASADO",IF(J21=TODAY(),"Hoje","Em dia"))))
H22: =IF(G22="","",CHOOSE(G22,"Lead","Atendimento","Visita","Proposta","Venda")) | J22: =IF(OR(G22="",I22="",L22="Sim"),"",I22+VLOOKUP(G22,$M$3:$N$7,2,FALSE)) | K22: =IF(L22="Sim","Perdido",IF(J22="","",IF(J22<TODAY(),"ATRASADO",IF(J22=TODAY(),"Hoje","Em dia"))))
H23: =IF(G23="","",CHOOSE(G23,"Lead","Atendimento","Visita","Proposta","Venda")) | J23: =IF(OR(G23="",I23="",L23="Sim"),"",I23+VLOOKUP(G23,$M$3:$N$7,2,FALSE)) | K23: =IF(L23="Sim","Perdido",IF(J23="","",IF(J23<TODAY(),"ATRASADO",IF(J23=TODAY(),"Hoje","Em dia"))))
H24: =IF(G24="","",CHOOSE(G24,"Lead","Atendimento","Visita","Proposta","Venda")) | J24: =IF(OR(G24="",I24="",L24="Sim"),"",I24+VLOOKUP(G24,$M$3:$N$7,2,FALSE)) | K24: =IF(L24="Sim","Perdido",IF(J24="","",IF(J24<TODAY(),"ATRASADO",IF(J24=TODAY(),"Hoje","Em dia"))))
... H509: =IF(G509="","",CHOOSE(G509,"Lead","Atendimento","Visita","Proposta","Venda")) | J509: =IF(OR(G509="",I509="",L509="Sim"),"",I509+VLOOKUP(G509,$M$3:$N$7,2,FALSE)) | K509: =IF(L509="Sim","Perdido",IF(J509="","",IF(J509<TODAY(),"ATRASADO",IF(J509=TODAY(),"Hoje","Em dia"))))

Sheet Painel
A1: Painel do funil
A2: Calculado a partir da aba Funil. Mostra suas taxas reais e o gargalo.
A4: Etapa | B4: Chegaram a esta etapa | C4: Conversão da etapa anterior
A5: Leads | B5: =COUNTIF(Funil!$G$10:$G$509,">=1")
A6: Atendimentos | B6: =COUNTIF(Funil!$G$10:$G$509,">=2") | C6: =IF(B5=0,"",B6/B5)
A7: Visitas | B7: =COUNTIF(Funil!$G$10:$G$509,">=3") | C7: =IF(B6=0,"",B7/B6)
A8: Propostas | B8: =COUNTIF(Funil!$G$10:$G$509,">=4") | C8: =IF(B7=0,"",B8/B7)
A9: Vendas | B9: =COUNTIF(Funil!$G$10:$G$509,5) | C9: =IF(B8=0,"",B9/B8)
A11: Leads atrasados (sem contato) | B11: =COUNTIF(Funil!$K$10:$K$509,"ATRASADO")
A12: Contatos para hoje | B12: =COUNTIF(Funil!$K$10:$K$509,"Hoje")
A13: Leads perdidos | B13: =COUNTIF(Funil!$L$10:$L$509,"Sim")
A15: GARGALO (menor conversão) | B15: =IF(COUNT(C6:C9)<4,"Registre mais leads para calcular",INDEX(A6:A9,MATCH(MIN(C6:C9),C6:C9,0)))
A17: Gargalo em Atendimentos: responda mais rápido. Em Visitas: qualifique melhor. Em Propostas: melhore a visita. Em Vendas: preço e negociação.

Sheet ACM
A1: Análise comparativa de mercado (ACM)
A2: Use de 5 a 10 imóveis parecidos. Marque 'Não' em 'Usar?' para descartar extremos.
A4: Imóvel avaliado | B4: Apto 2 dorms, Rua X (exemplo)
A5: Área (m²) | B5: 65
A6: Ajuste (%) para diferenças: andar, vaga, reforma, sol... | B6: 0 | C6: Ex.: +5% se o avaliado é reformado e os demais não; −5% se não tem vaga.
A8: Endereço / condomínio | B8: Área (m²) | C8: Preço (R$) | D8: Fonte | E8: Usar? | F8: Preço por m² | G8: Considerado
A9: Cond. A (exemplo) | B9: 62 | C9: 520000 | D9: Anúncio | E9: Sim | F9: =IF(OR(B9="",C9="",B9=0),"",C9/B9) | G9: =IF(AND(E9="Sim",F9<>""),F9,"")
A10: Cond. B (exemplo) | B10: 70 | C10: 560000 | D10: Anúncio | E10: Sim | F10: =IF(OR(B10="",C10="",B10=0),"",C10/B10) | G10: =IF(AND(E10="Sim",F10<>""),F10,"")
A11: Cond. C (exemplo) | B11: 64 | C11: 505000 | D11: Anúncio | E11: Sim | F11: =IF(OR(B11="",C11="",B11=0),"",C11/B11) | G11: =IF(AND(E11="Sim",F11<>""),F11,"")
A12: Cond. D (exemplo) | B12: 68 | C12: 590000 | D12: Anúncio | E12: Sim | F12: =IF(OR(B12="",C12="",B12=0),"",C12/B12) | G12: =IF(AND(E12="Sim",F12<>""),F12,"")
A13: Cond. E (exemplo) | B13: 60 | C13: 470000 | D13: Anúncio | E13: Sim | F13: =IF(OR(B13="",C13="",B13=0),"",C13/B13) | G13: =IF(AND(E13="Sim",F13<>""),F13,"")
F14: =IF(OR(B14="",C14="",B14=0),"",C14/B14) | G14: =IF(AND(E14="Sim",F14<>""),F14,"")
F15: =IF(OR(B15="",C15="",B15=0),"",C15/B15) | G15: =IF(AND(E15="Sim",F15<>""),F15,"")
F16: =IF(OR(B16="",C16="",B16=0),"",C16/B16) | G16: =IF(AND(E16="Sim",F16<>""),F16,"")
F17: =IF(OR(B17="",C17="",B17=0),"",C17/B17) | G17: =IF(AND(E17="Sim",F17<>""),F17,"")
F18: =IF(OR(B18="",C18="",B18=0),"",C18/B18) | G18: =IF(AND(E18="Sim",F18<>""),F18,"")
F19: =IF(OR(B19="",C19="",B19=0),"",C19/B19) | G19: =IF(AND(E19="Sim",F19<>""),F19,"")
F20: =IF(OR(B20="",C20="",B20=0),"",C20/B20) | G20: =IF(AND(E20="Sim",F20<>""),F20,"")
A23: Comparáveis considerados | B23: =COUNT(G9:G20)
A24: Menor preço por m² | B24: =IF(B23=0,"",MIN(G9:G20))
A25: Maior preço por m² | B25: =IF(B23=0,"",MAX(G9:G20))
A26: Média do m² | B26: =IF(B23=0,"",AVERAGE(G9:G20))
A27: Mediana do m² (mais confiável) | B27: =IF(B23=0,"",MEDIAN(G9:G20))
A28: VALOR DE REFERÊNCIA | B28: =IF(B23=0,"",B27*B5*(1+B6))
A29: Faixa sugerida: de | B29: =IF(B23=0,"",B28*0.95)
A30: Faixa sugerida: até | B30: =IF(B23=0,"",B28*1.05)
A32: Preço de anúncio costuma ter margem de negociação. Sempre que tiver valores de venda real, prefira-os. Leve o resultado ao Prompt 7.

Sheet Captações
A1: Captações e exclusividades
A2: Alertas automáticos: exclusividade vencendo e imóvel parado que precisa de revisão de preço.
A4: Imóvel | B4: Proprietário | C4: Bairro | D4: Preço anunciado | E4: Data da captação | F4: Exclusivo? | G4: Prazo (dias) | H4: Exclusividade até | I4: Dias anunciado | J4: Visitas | K4: Propostas | L4: Alerta
A5: Apto 2 dorms (exemplo) | C5: Tatuapé | D5: 540000 | E5: =TODAY()-40 | F5: Sim | G5: 90 | H5: =IF(OR(F5<>"Sim",E5="",G5=""),"",E5+G5) | I5: =IF(E5="","",TODAY()-E5) | J5: 2 | K5: 0 | L5: =IF(E5="","",IF(AND(H5<>"",H5<TODAY()),"Exclusividade vencida",IF(AND(H5<>"",H5-TODAY()<=15),"Renovar exclusividade",IF(AND(I5>=30,N(J5)<3),"Revisar preço (poucas visitas)",IF(AND(I5>=60,N(K5)=0),"Revisar preço (sem propostas)","OK")))))
H6: =IF(OR(F6<>"Sim",E6="",G6=""),"",E6+G6) | I6: =IF(E6="","",TODAY()-E6) | L6: =IF(E6="","",IF(AND(H6<>"",H6<TODAY()),"Exclusividade vencida",IF(AND(H6<>"",H6-TODAY()<=15),"Renovar exclusividade",IF(AND(I6>=30,N(J6)<3),"Revisar preço (poucas visitas)",IF(AND(I6>=60,N(K6)=0),"Revisar preço (sem propostas)","OK")))))
H7: =IF(OR(F7<>"Sim",E7="",G7=""),"",E7+G7) | I7: =IF(E7="","",TODAY()-E7) | L7: =IF(E7="","",IF(AND(H7<>"",H7<TODAY()),"Exclusividade vencida",IF(AND(H7<>"",H7-TODAY()<=15),"Renovar exclusividade",IF(AND(I7>=30,N(J7)<3),"Revisar preço (poucas visitas)",IF(AND(I7>=60,N(K7)=0),"Revisar preço (sem propostas)","OK")))))
H8: =IF(OR(F8<>"Sim",E8="",G8=""),"",E8+G8) | I8: =IF(E8="","",TODAY()-E8) | L8: =IF(E8="","",IF(AND(H8<>"",H8<TODAY()),"Exclusividade vencida",IF(AND(H8<>"",H8-TODAY()<=15),"Renovar exclusividade",IF(AND(I8>=30,N(J8)<3),"Revisar preço (poucas visitas)",IF(AND(I8>=60,N(K8)=0),"Revisar preço (sem propostas)","OK")))))
H9: =IF(OR(F9<>"Sim",E9="",G9=""),"",E9+G9) | I9: =IF(E9="","",TODAY()-E9) | L9: =IF(E9="","",IF(AND(H9<>"",H9<TODAY()),"Exclusividade vencida",IF(AND(H9<>"",H9-TODAY()<=15),"Renovar exclusividade",IF(AND(I9>=30,N(J9)<3),"Revisar preço (poucas visitas)",IF(AND(I9>=60,N(K9)=0),"Revisar preço (sem propostas)","OK")))))
H10: =IF(OR(F10<>"Sim",E10="",G10=""),"",E10+G10) | I10: =IF(E10="","",TODAY()-E10) | L10: =IF(E10="","",IF(AND(H10<>"",H10<TODAY()),"Exclusividade vencida",IF(AND(H10<>"",H10-TODAY()<=15),"Renovar exclusividade",IF(AND(I10>=30,N(J10)<3),"Revisar preço (poucas visitas)",IF(AND(I10>=60,N(K10)=0),"Revisar preço (sem propostas)","OK")))))
H11: =IF(OR(F11<>"Sim",E11="",G11=""),"",E11+G11) | I11: =IF(E11="","",TODAY()-E11) | L11: =IF(E11="","",IF(AND(H11<>"",H11<TODAY()),"Exclusividade vencida",IF(AND(H11<>"",H11-TODAY()<=15),"Renovar exclusividade",IF(AND(I11>=30,N(J11)<3),"Revisar preço (poucas visitas)",IF(AND(I11>=60,N(K11)=0),"Revisar preço (sem propostas)","OK")))))
H12: =IF(OR(F12<>"Sim",E12="",G12=""),"",E12+G12) | I12: =IF(E12="","",TODAY()-E12) | L12: =IF(E12="","",IF(AND(H12<>"",H12<TODAY()),"Exclusividade vencida",IF(AND(H12<>"",H12-TODAY()<=15),"Renovar exclusividade",IF(AND(I12>=30,N(J12)<3),"Revisar preço (poucas visitas)",IF(AND(I12>=60,N(K12)=0),"Revisar preço (sem propostas)","OK")))))
H13: =IF(OR(F13<>"Sim",E13="",G13=""),"",E13+G13) | I13: =IF(E13="","",TODAY()-E13) | L13: =IF(E13="","",IF(AND(H13<>"",H13<TODAY()),"Exclusividade vencida",IF(AND(H13<>"",H13-TODAY()<=15),"Renovar exclusividade",IF(AND(I13>=30,N(J13)<3),"Revisar preço (poucas visitas)",IF(AND(I13>=60,N(K13)=0),"Revisar preço (sem propostas)","OK")))))
H14: =IF(OR(F14<>"Sim",E14="",G14=""),"",E14+G14) | I14: =IF(E14="","",TODAY()-E14) | L14: =IF(E14="","",IF(AND(H14<>"",H14<TODAY()),"Exclusividade vencida",IF(AND(H14<>"",H14-TODAY()<=15),"Renovar exclusividade",IF(AND(I14>=30,N(J14)<3),"Revisar preço (poucas visitas)",IF(AND(I14>=60,N(K14)=0),"Revisar preço (sem propostas)","OK")))))
H15: =IF(OR(F15<>"Sim",E15="",G15=""),"",E15+G15) | I15: =IF(E15="","",TODAY()-E15) | L15: =IF(E15="","",IF(AND(H15<>"",H15<TODAY()),"Exclusividade vencida",IF(AND(H15<>"",H15-TODAY()<=15),"Renovar exclusividade",IF(AND(I15>=30,N(J15)<3),"Revisar preço (poucas visitas)",IF(AND(I15>=60,N(K15)=0),"Revisar preço (sem propostas)","OK")))))
H16: =IF(OR(F16<>"Sim",E16="",G16=""),"",E16+G16) | I16: =IF(E16="","",TODAY()-E16) | L16: =IF(E16="","",IF(AND(H16<>"",H16<TODAY()),"Exclusividade vencida",IF(AND(H16<>"",H16-TODAY()<=15),"Renovar exclusividade",IF(AND(I16>=30,N(J16)<3),"Revisar preço (poucas visitas)",IF(AND(I16>=60,N(K16)=0),"Revisar preço (sem propostas)","OK")))))
H17: =IF(OR(F17<>"Sim",E17="",G17=""),"",E17+G17) | I17: =IF(E17="","",TODAY()-E17) | L17: =IF(E17="","",IF(AND(H17<>"",H17<TODAY()),"Exclusividade vencida",IF(AND(H17<>"",H17-TODAY()<=15),"Renovar exclusividade",IF(AND(I17>=30,N(J17)<3),"Revisar preço (poucas visitas)",IF(AND(I17>=60,N(K17)=0),"Revisar preço (sem propostas)","OK")))))
... H104: =IF(OR(F104<>"Sim",E104="",G104=""),"",E104+G104) | I104: =IF(E104="","",TODAY()-E104) | L104: =IF(E104="","",IF(AND(H104<>"",H104<TODAY()),"Exclusividade vencida",IF(AND(H104<>"",H104-TODAY()<=15),"Renovar exclusividade",IF(AND(I104>=30,N(J104)<3),"Revisar preço (poucas visitas)",IF(AND(I104>=60,N(K104)=0),"Revisar preço (sem propostas)","OK")))))

Sheet Comissões
A1: Comissões
A2: Controle do que foi recebido e do que está a receber.
A4: Data da venda | B4: Imóvel | C4: Valor da venda | D4: Comissão (%) | E4: Minha parte (%) | F4: Comissão total | G4: Minha comissão | H4: Recebido? | J4: Total de vendas (VGV) | K4: =SUM(C5:C104)
F5: =IF(C5="","",C5*D5) | G5: =IF(C5="","",F5*E5) | J5: Minha comissão total | K5: =SUM(G5:G104)
F6: =IF(C6="","",C6*D6) | G6: =IF(C6="","",F6*E6) | J6: Recebido | K6: =SUMIF(H5:H104,"Sim",G5:G104)
F7: =IF(C7="","",C7*D7) | G7: =IF(C7="","",F7*E7) | J7: A receber | K7: =K5-K6
F8: =IF(C8="","",C8*D8) | G8: =IF(C8="","",F8*E8)
F9: =IF(C9="","",C9*D9) | G9: =IF(C9="","",F9*E9)
F10: =IF(C10="","",C10*D10) | G10: =IF(C10="","",F10*E10)
F11: =IF(C11="","",C11*D11) | G11: =IF(C11="","",F11*E11)
F12: =IF(C12="","",C12*D12) | G12: =IF(C12="","",F12*E12)
F13: =IF(C13="","",C13*D13) | G13: =IF(C13="","",F13*E13)
F14: =IF(C14="","",C14*D14) | G14: =IF(C14="","",F14*E14)
F15: =IF(C15="","",C15*D15) | G15: =IF(C15="","",F15*E15)
F16: =IF(C16="","",C16*D16) | G16: =IF(C16="","",F16*E16)
F17: =IF(C17="","",C17*D17) | G17: =IF(C17="","",F17*E17)
F18: =IF(C18="","",C18*D18) | G18: =IF(C18="","",F18*E18)
F19: =IF(C19="","",C19*D19) | G19: =IF(C19="","",F19*E19)
... F104: =IF(C104="","",C104*D104) | G104: =IF(C104="","",F104*E104)

Sheet Simuladores
A1: Simuladores (estimativas)
A2: Valores aproximados para orientar a conversa. Os oficiais vêm do banco, da prefeitura e do cartório.
A4: 1. CUSTOS DA COMPRA
A5: Valor do imóvel | B5: 500000
A6: Alíquota do ITBI da cidade (%) | B6: 0.03 | C6: Confirme a alíquota e a base de cálculo na prefeitura.
A7: Escritura + registro (estimativa, % do valor) | B7: 0.015
A8: Avaliação e taxas do banco (R$) | B8: 3500
A9: ITBI estimado | B9: =B5*B6
A10: Escritura e registro estimados | B10: =B5*B7
A11: TOTAL DE CUSTOS | B11: =B9+B10+B8
A12: % do valor do imóvel | B12: =IF(B5=0,0,B11/B5)
A15: 2. FINANCIAMENTO: SAC x PRICE
A16: Valor do imóvel | B16: 500000
A17: Entrada (%) | B17: 0.2
A18: Juros ao ano (%) | B18: 0.115
A19: Prazo (meses) | B19: 360
A20: Valor da entrada | B20: =B16*B17
A21: Valor financiado | B21: =B16-B20
A22: Juros ao mês (equivalente) | B22: =(1+B18)^(1/12)-1
A23: PRICE: parcela fixa | B23: =IF(B22=0,B21/B19,B21*B22/(1-(1+B22)^(-B19)))
A24: SAC: primeira parcela | B24: =B21/B19+B21*B22
A25: SAC: última parcela | B25: =B21/B19*(1+B22)
A26: PRICE: total de juros | B26: =B23*B19-B21
A27: SAC: total de juros | B27: =B22*B21*(B19+1)/2
A28: Renda mínima estimada (parcela = 30% da renda) PRICE | B28: =B23/0.3
A29: Renda mínima estimada (parcela = 30% da renda) SAC | B29: =B24/0.3
A31: Sem seguros obrigatórios, taxas administrativas e correção monetária. O banco informa o CET oficial.
A34: 3. RENTABILIDADE DE ALUGUEL (investidor)
A35: Preço do imóvel | B35: 350000
A36: Aluguel mensal | B36: 2000
A37: Custos mensais do proprietário (IPTU, cond. se vago etc.) | B37: 150
A38: Taxa de administração (%) | B38: 0.08
A39: Meses vagos por ano (estimativa) | B39: 1
A40: Rentabilidade bruta ao ano | B40: =IF(B35=0,0,B36*12/B35)
A41: Renda líquida no ano | B41: =B36*(12-B39)*(1-B38)-B37*12
A42: Rentabilidade líquida ao ano | B42: =IF(B35=0,0,B41/B35)
A43: Rentabilidade líquida ao mês | B43: =(1+B42)^(1/12)-1
A45: Antes de impostos sobre aluguel e sem considerar valorização. Não é recomendação de investimento.

Sheet Calendário 30 dias
A1: Calendário de conteúdo: 30 dias
A2: Gere a semana inteira no domingo com o Prompt 40.
A4: Dia | B4: Semana / foco | C4: Dia da semana | D4: Tipo | E4: Ideia | F4: Prompt | G4: Feito?
A5: 1 | B5: 1 · Apresentação e território | C5: Seg | D5: Imóvel | E5: Tour em vídeo do imóvel da semana | F5: 6
A6: 2 | B6: 1 · Apresentação e território | C6: Ter | D6: Educação | E6: Dica para comprador (financiamento, custos, documentos) | F6: 30
A7: 3 | B7: 1 · Apresentação e território | C7: Qua | D7: Bairro | E7: Guia do bairro em carrossel | F7: 41
A8: 4 | B8: 1 · Apresentação e território | C8: Qui | D8: Imóvel | E8: Imóvel no feed com legenda | F8: 5
A9: 5 | B9: 1 · Apresentação e território | C9: Sex | D9: Mercado | E9: Preço por m² ou conteúdo para proprietários | F9: 43
A10: 6 | B10: 1 · Apresentação e território | C10: Sáb | D10: Prova | E10: Vendido, chave entregue ou depoimento | F10: 42
A11: 7 | B11: 1 · Apresentação e território | C11: Dom | D11: Planejamento | E11: Gerar os conteúdos da semana | F11: 40
A12: 8 | B12: 2 · Compradores | C12: Seg | D12: Imóvel | E12: Tour em vídeo do imóvel da semana | F12: 6
A13: 9 | B13: 2 · Compradores | C13: Ter | D13: Educação | E13: Dica para comprador (financiamento, custos, documentos) | F13: 30
A14: 10 | B14: 2 · Compradores | C14: Qua | D14: Bairro | E14: Guia do bairro em carrossel | F14: 41
A15: 11 | B15: 2 · Compradores | C15: Qui | D15: Imóvel | E15: Imóvel no feed com legenda | F15: 5
A16: 12 | B16: 2 · Compradores | C16: Sex | D16: Mercado | E16: Preço por m² ou conteúdo para proprietários | F16: 43
... A34: 30 | B34: 5 · Revisão | C34: Ter | D34: Educação | E34: Dica para comprador (financiamento, custos, documentos) | F34: 30
